odoo8_addon_base_import_async-8.0.1.0.0.99.dev6-py2.7-nspkg.pth
odoo8_addon_base_import_async-8.0.1.0.0.99.dev6.dist-info/METADATA
odoo8_addon_base_import_async-8.0.1.0.0.99.dev6.dist-info/RECORD
odoo8_addon_base_import_async-8.0.1.0.0.99.dev6.dist-info/WHEEL
odoo8_addon_base_import_async-8.0.1.0.0.99.dev6.dist-info/namespace_packages.txt
odoo8_addon_base_import_async-8.0.1.0.0.99.dev6.dist-info/top_level.txt
odoo_addons/base_import_async/README.rst
odoo_addons/base_import_async/__init__.py
odoo_addons/base_import_async/__openerp__.py
odoo_addons/base_import_async/models/__init__.py
odoo_addons/base_import_async/models/base_import_async.py
odoo_addons/base_import_async/static/description/icon.png
odoo_addons/base_import_async/static/src/js/import.js
odoo_addons/base_import_async/static/src/xml/import.xml
odoo_addons/base_import_async/views/base_import_async.xml
